webweb/__init__.py
webweb/webweb.py
webweb-0.0.2.dist-info/METADATA
webweb-0.0.2.dist-info/WHEEL
webweb-0.0.2.dist-info/top_level.txt
webweb-0.0.2.dist-info/RECORD
